actxps/__init__.py
actxps/actxpspy.egg-info/dependency_links.txt
actxps/actxpspy.egg-info/PKG-INFO
actxps/actxpspy.egg-info/requires.txt
actxps/actxpspy.egg-info/SOURCES.txt
actxps/actxpspy.egg-info/top_level.txt
actxps/col_select.py
actxps/data/account_vals
actxps/data/agg_sim_dat
actxps/data/census_dat
actxps/data/create_data.py
actxps/data/qx_iamb.csv
actxps/data/scaleG2.csv
actxps/data/toy_census.csv
actxps/data/withdrawals
actxps/datasets.py
actxps/dates.py
actxps/exp_shiny.py
actxps/exp_stats.py
actxps/expose.py
actxps/expose_split.py
actxps/tools.py
actxps/trx_stats.py
actxps-1.1.0.dist-info/LICENSE
actxps-1.1.0.dist-info/METADATA
actxps-1.1.0.dist-info/WHEEL
actxps-1.1.0.dist-info/RECORD
