Metadata-Version: 2.1
Name: actxps
Version: 1.1.0
Summary: Create Actuarial Experience Studies: Prepare Data, Summarize Results, and Create Reports
Home-page: https://github.com/mattheaphy/actxpspy
License: MIT
Author: Matt Heaphy
Author-email: mattrmattrs@gmail.com
Requires-Python: >=3.10
Classifier: License :: OSI Approved :: MIT License
Classifier: Programming Language :: Python :: 3
Classifier: Programming Language :: Python :: 3.10
Classifier: Programming Language :: Python :: 3.11
Classifier: Programming Language :: Python :: 3.12
Requires-Dist: faicons (>=0.2.2)
Requires-Dist: great-tables (>=0.3.1)
Requires-Dist: joblib (>=1.3.2)
Requires-Dist: matplotlib (>=3.8.2)
Requires-Dist: numpy (>=1.26.2)
Requires-Dist: pandas (>=2.1.4)
Requires-Dist: plotnine (>=0.12.4)
Requires-Dist: polars (>=0.20.9)
Requires-Dist: pyarrow (>=15.0.0)
Requires-Dist: scikit-misc (>=0.3.1)
Requires-Dist: scipy (>=1.11.4)
Requires-Dist: selenium (>=4.18.1,<5.0.0)
Requires-Dist: shiny (>=0.7.0)
Requires-Dist: shinyswatch (>=0.4.2)
Project-URL: Bug Tracker, https://github.com/mattheaphy/actxpspy/issues
Project-URL: Documentation, https://mattheaphy.github.io/actxpspy
Project-URL: Repository, https://github.com/mattheaphy/actxpspy
